{"name":"Fpcounter","tagline":"Automatic calculation of FP based on the code in an SCM","body":"# FPCounter\r\nAutomatic calculation of FP based on the code stored in a SCM\r\n\r\nThis tool allows you to count the function points of a project stored on a SCM.\r\nCurrently the tool works by connecting to one or more instances of MS Team Foundation Server, to one or more collection. \r\nFor each collection it selects individual projects, then laws  Work Item custom \"CI Software\"  to get the name of the path\r\nto be analyzed and writes the results in the custom work item named QAReport\r\n","google":"","note":"Don't delete this file! It's used internally to help with page regeneration."}